clipkg/__init__.py
clipkg/__main__.py
clitest-0.3.2.dist-info/DESCRIPTION.rst
clitest-0.3.2.dist-info/METADATA
clitest-0.3.2.dist-info/RECORD
clitest-0.3.2.dist-info/WHEEL
clitest-0.3.2.dist-info/metadata.json
clitest-0.3.2.dist-info/top_level.txt
