Metadata-Version: 2.0
Name: clitest
Version: 0.3.2
Summary: My short description for my project.
Home-page: https://github.com/colinlixa/pythontest
Author: Awesome Soul
Author-email: me@example.com
License: MIT
Platform: UNKNOWN
Classifier: License :: OSI Approved :: MIT License
Classifier: Programming Language :: Python
Classifier: Programming Language :: Python :: 3
Classifier: Programming Language :: Python :: 3.6
Classifier: Programming Language :: Python :: Implementation :: CPython
Classifier: Programming Language :: Python :: Implementation :: PyPy
Requires-Python: >=2.7.0
Requires-Dist: requests
